DDLab11/example/2/32optimizempy.v
`timescale 1ns/1ps
module lab(CLK, RST, in_a, in_b, Product, Product_Valid);
input CLK, RST;
input [31:0]	in_a;	// Multiplicand
input [31:0]	in_b;// Multiplier
output reg [63:0] Product;
output reg Product_Valid;

reg [31:0] Mplicand;
reg [31:0] Mplier;
reg [6:0]	Counter ;
reg	sign;

//Counter
always @(posedge CLK or posedge RST)
begin
	if(RST)
		Counter <=6'b0;
	else
		Counter <= Counter +6'b1;
end

always @(negedge CLK)
begin
	if(Counter<=6'd32)
		Product <= Product >>1;
end

//Multiplier
always @(posedge CLK or posedge RST)
begin
	//初始化數值
	if(RST) begin
		Product  <= 64'b0;
		Mplicand <= 32'b0;
		Mplier   <= 32'b0;	
	end 
	
	//輸入乘數與被乘數
	else if(Counter == 6'd0) begin
		Mplicand <= in_a;
		Mplier <= in_b;
	end 
	
	//乘法與數值移位
	/* write down your design below */
	else if(Counter <=6'd32) 
	begin
		//Product=Product>>1;
		if(Mplier[0] == 1'b1) begin
			Product[63:31] <= Mplicand + Product[63:31];
		end
		//Mplicand <= Mplicand << 1'b1;
		Mplier <= Mplier >> 1'b1;
	end 
	/* write down your design upon */
end

//判斷輸出
always @(posedge CLK or posedge RST)
begin
	if(RST)
		Product_Valid <=1'b0;
	else if(Counter==6'd32)
		Product_Valid <=1'b1;
	else
		Product_Valid <=1'b0;
end

endmodule

DDLab11/example/2/tb32optimizempy.v
`timescale 1ns/1ps
`include "32optimizempy.v"

module tb_lab();
reg [31:0] in_a;
reg [31:0] in_b;
reg CLK;
reg reset;
wire [63:0] out;
wire out_valid;

reg [5:0]	count;
reg signed [64:0]	correct_ans;
reg error;
reg signed [63:0]	 temp_a;
reg signed [63:0]	temp_b;

lab m1(CLK, reset, in_a, in_b, out, out_valid);

initial begin
	$dumpfile("lab11.vcd");  //gtkwave
	$dumpvars;
	CLK = 1'b0;
	
	#10 reset = 1;//正數*正數
	temp_a = 32'd30;
	temp_b = 32'd90;
	#20 reset = 0;
	
	#680 reset = 1;//正數*負數
	temp_a = 32'd30;
	temp_b = -32'd90;
	#20 reset = 0;
	
	#680 reset = 1;//負數*正數
	temp_a = -32'd30;
	temp_b = 32'd90;
	#20 reset = 0;
	
	#680 reset = 1;//負數*負數
	temp_a = -32'd30;
	temp_b = -32'd90;
	#20 reset = 0;

	#680 reset = 1;//無號最大數*無號最大數
	temp_a = 64'd4294967295;
	temp_b = 64'd4294967295;
	#20 reset = 0;
	
	#680 reset = 1;//無號溢位數*1
	temp_a = 64'd4294967296;
	temp_b = 64'd1;
	#20 reset = 0;
	
	#680 reset = 1;//無號溢位數*1
	temp_a = 64'd4294967297;
	temp_b = 64'd1;
	#20 reset = 0;

	#680 $finish;
end

always #10 CLK = ~CLK;

always @(posedge CLK or posedge reset)
begin
	if(reset)//初始化
	begin
		count <= 0;
		in_a <= temp_a;
		in_b <= temp_b;
		correct_ans <= 0;
		error <= 0;
	end

	else//對答案
	begin
		correct_ans <= temp_a *temp_b;
		count <= count +1;

		if(out_valid==1)
			if(out != correct_ans)
			begin
				error <=1;
				$display ();
				$display ("// Fail //");
				$display ("//%d * %d = ?",temp_a, temp_b);
				$display ("//your answer is %d, but correct answer is %d\n",
				out, correct_ans);
			end
			
			else
			begin
				error <= 0;
				$display ();
				$display ("// Successful //");
				$display ("//%d * %d = ?",temp_a, temp_b);
				$display ("//your answer is %d,  correct answer is %d\n",
				out, correct_ans);
			end
	end
end

endmodule

DDLab11/example/2/lab11.vcd
$date
	Wed May 30 19:37:31 2018
$end
$version
	Icarus Verilog
$end
$timescale
	1ps
$end
$scope module tb_lab $end
$var wire 1 ! out_valid $end
$var wire 64 " out [63:0] $end
$var reg 1 # CLK $end
$var reg 65 $ correct_ans [64:0] $end
$var reg 6 % count [5:0] $end
$var reg 1 & error $end
$var reg 32 ' in_a [31:0] $end
$var reg 32 ( in_b [31:0] $end
$var reg 1 ) reset $end
$var reg 64 * temp_a [63:0] $end
$var reg 64 + temp_b [63:0] $end
$scope module m1 $end
$var wire 1 # CLK $end
$var wire 1 ) RST $end
$var wire 32 , in_a [31:0] $end
$var wire 32 - in_b [31:0] $end
$var reg 7 . Counter [6:0] $end
$var reg 32 / Mplicand [31:0] $end
$var reg 32 0 Mplier [31:0] $end
$var reg 64 1 Product [63:0] $end
$var reg 1 ! Product_Valid $end
$upscope $end
$upscope $end
$enddefinitions $end
#0
$dumpvars
bx 1
bx 0
bx /
bx .
bx -
bx ,
bx +
bx *
x)
bx (
bx '
x&
bx %
bx $
0#
bx "
x!
$end
#10000
b0 .
b0 0
b0 /
b0 "
b0 1
0!
0&
b0 $
b1011010 (
b1011010 -
b11110 '
b11110 ,
b0 %
1#
b1011010 +
b11110 *
1)
#20000
0#
#30000
b1 %
b101010001100 $
b1011010 0
b11110 /
b1 .
1#
0)
#40000
0#
#50000
b10 .
b101101 0
b10 %
1#
#60000
0#
#70000
b11 %
b10110 0
b111100000000000000000000000000000000 "
b111100000000000000000000000000000000 1
b11 .
1#
#80000
b11110000000000000000000000000000000 "
b11110000000000000000000000000000000 1
0#
#90000
b100 .
b1011 0
b100 %
1#
#100000
b1111000000000000000000000000000000 "
b1111000000000000000000000000000000 1
0#
#110000
b101 %
b101 0
b1001011000000000000000000000000000000 "
b1001011000000000000000000000000000000 1
b101 .
1#
#120000
b100101100000000000000000000000000000 "
b100101100000000000000000000000000000 1
0#
#130000
b110 .
b10 0
b1100001100000000000000000000000000000 "
b1100001100000000000000000000000000000 1
b110 %
1#
#140000
b110000110000000000000000000000000000 "
b110000110000000000000000000000000000 1
0#
#150000
b111 %
b1 0
b111 .
1#
#160000
b11000011000000000000000000000000000 "
b11000011000000000000000000000000000 1
0#
#170000
b1000 .
b0 0
b1010100011000000000000000000000000000 "
b1010100011000000000000000000000000000 1
b1000 %
1#
#180000
b101010001100000000000000000000000000 "
b101010001100000000000000000000000000 1
0#
#190000
b1001 %
b1001 .
1#
#200000
b10101000110000000000000000000000000 "
b10101000110000000000000000000000000 1
0#
#210000
b1010 .
b1010 %
1#
#220000
b1010100011000000000000000000000000 "
b1010100011000000000000000000000000 1
0#
#230000
b1011 %
b1011 .
1#
#240000
b101010001100000000000000000000000 "
b101010001100000000000000000000000 1
0#
#250000
b1100 .
b1100 %
1#
#260000
b10101000110000000000000000000000 "
b10101000110000000000000000000000 1
0#
#270000
b1101 %
b1101 .
1#
#280000
b1010100011000000000000000000000 "
b1010100011000000000000000000000 1
0#
#290000
b1110 .
b1110 %
1#
#300000
b101010001100000000000000000000 "
b101010001100000000000000000000 1
0#
#310000
b1111 %
b1111 .
1#
#320000
b10101000110000000000000000000 "
b10101000110000000000000000000 1
0#
#330000
b10000 .
b10000 %
1#
#340000
b1010100011000000000000000000 "
b1010100011000000000000000000 1
0#
#350000
b10001 %
b10001 .
1#
#360000
b101010001100000000000000000 "
b101010001100000000000000000 1
0#
#370000
b10010 .
b10010 %
1#
#380000
b10101000110000000000000000 "
b10101000110000000000000000 1
0#
#390000
b10011 %
b10011 .
1#
#400000
b1010100011000000000000000 "
b1010100011000000000000000 1
0#
#410000
b10100 .
b10100 %
1#
#420000
b101010001100000000000000 "
b101010001100000000000000 1
0#
#430000
b10101 %
b10101 .
1#
#440000
b10101000110000000000000 "
b10101000110000000000000 1
0#
#450000
b10110 .
b10110 %
1#
#460000
b1010100011000000000000 "
b1010100011000000000000 1
0#
#470000
b10111 %
b10111 .
1#
#480000
b101010001100000000000 "
b101010001100000000000 1
0#
#490000
b11000 .
b11000 %
1#
#500000
b10101000110000000000 "
b10101000110000000000 1
0#
#510000
b11001 %
b11001 .
1#
#520000
b1010100011000000000 "
b1010100011000000000 1
0#
#530000
b11010 .
b11010 %
1#
#540000
b101010001100000000 "
b101010001100000000 1
0#
#550000
b11011 %
b11011 .
1#
#560000
b10101000110000000 "
b10101000110000000 1
0#
#570000
b11100 .
b11100 %
1#
#580000
b1010100011000000 "
b1010100011000000 1
0#
#590000
b11101 %
b11101 .
1#
#600000
b101010001100000 "
b101010001100000 1
0#
#610000
b11110 .
b11110 %
1#
#620000
b10101000110000 "
b10101000110000 1
0#
#630000
b11111 %
b11111 .
1#
#640000
b1010100011000 "
b1010100011000 1
0#
#650000
b100000 .
b100000 %
1#
#660000
b101010001100 "
b101010001100 1
0#
#670000
b100001 %
1!
b100001 .
1#
#680000
0#
#690000
b100010 .
0!
b100010 %
1#
#700000
0#
#710000
b0 $
b11111111111111111111111110100110 (
b11111111111111111111111110100110 -
b0 %
b0 /
b0 "
b0 1
b0 .
1#
b1111111111111111111111111111111111111111111111111111111110100110 +
1)
#720000
0#
#730000
b1 .
b11111111111111111111111110100110 0
b11110 /
b1 %
b11111111111111111111111111111111111111111111111111111010101110100 $
1#
0)
#740000
0#
#750000
b10 %
b1111111111111111111111111010011 0
b10 .
1#
#760000
0#
#770000
b11 .
b111111111111111111111111101001 0
b111100000000000000000000000000000000 "
b111100000000000000000000000000000000 1
b11 %
1#
#780000
b11110000000000000000000000000000000 "
b11110000000000000000000000000000000 1
0#
#790000
b100 %
b11111111111111111111111110100 0
b1011010000000000000000000000000000000 "
b1011010000000000000000000000000000000 1
b100 .
1#
#800000
b101101000000000000000000000000000000 "
b101101000000000000000000000000000000 1
0#
#810000
b101 .
b1111111111111111111111111010 0
b101 %
1#
#820000
b10110100000000000000000000000000000 "
b10110100000000000000000000000000000 1
0#
#830000
b110 %
b111111111111111111111111101 0
b110 .
1#
#840000
b1011010000000000000000000000000000 "
b1011010000000000000000000000000000 1
0#
#850000
b111 .
b11111111111111111111111110 0
b1000111010000000000000000000000000000 "
b1000111010000000000000000000000000000 1
b111 %
1#
#860000
b100011101000000000000000000000000000 "
b100011101000000000000000000000000000 1
0#
#870000
b1000 %
b1111111111111111111111111 0
b1000 .
1#
#880000
b10001110100000000000000000000000000 "
b10001110100000000000000000000000000 1
0#
#890000
b1001 .
b111111111111111111111111 0
b1001101110100000000000000000000000000 "
b1001101110100000000000000000000000000 1
b1001 %
1#
#900000
b100110111010000000000000000000000000 "
b100110111010000000000000000000000000 1
0#
#910000
b1010 %
b11111111111111111111111 0
b1100010111010000000000000000000000000 "
b1100010111010000000000000000000000000 1
b1010 .
1#
#920000
b110001011101000000000000000000000000 "
b110001011101000000000000000000000000 1
0#
#930000
b1011 .
b1111111111111111111111 0
b1101101011101000000000000000000000000 "
b1101101011101000000000000000000000000 1
b1011 %
1#
#940000
b110110101110100000000000000000000000 "
b110110101110100000000000000000000000 1
0#
#950000
b1100 %
b111111111111111111111 0
b1110010101110100000000000000000000000 "
b1110010101110100000000000000000000000 1
b1100 .
1#
#960000
b111001010111010000000000000000000000 "
b111001010111010000000000000000000000 1
0#
#970000
b1101 .
b11111111111111111111 0
b1110101010111010000000000000000000000 "
b1110101010111010000000000000000000000 1
b1101 %
1#
#980000
b111010101011101000000000000000000000 "
b111010101011101000000000000000000000 1
0#
#990000
b1110 %
b1111111111111111111 0
b1110110101011101000000000000000000000 "
b1110110101011101000000000000000000000 1
b1110 .
1#
#1000000
b111011010101110100000000000000000000 "
b111011010101110100000000000000000000 1
0#
#1010000
b1111 .
b111111111111111111 0
b1110111010101110100000000000000000000 "
b1110111010101110100000000000000000000 1
b1111 %
1#
#1020000
b111011101010111010000000000000000000 "
b111011101010111010000000000000000000 1
0#
#1030000
b10000 %
b11111111111111111 0
b1110111101010111010000000000000000000 "
b1110111101010111010000000000000000000 1
b10000 .
1#
#1040000
b111011110101011101000000000000000000 "
b111011110101011101000000000000000000 1
0#
#1050000
b10001 .
b1111111111111111 0
b1110111110101011101000000000000000000 "
b1110111110101011101000000000000000000 1
b10001 %
1#
#1060000
b111011111010101110100000000000000000 "
b111011111010101110100000000000000000 1
0#
#1070000
b10010 %
b111111111111111 0
b1110111111010101110100000000000000000 "
b1110111111010101110100000000000000000 1
b10010 .
1#
#1080000
b111011111101010111010000000000000000 "
b111011111101010111010000000000000000 1
0#
#1090000
b10011 .
b11111111111111 0
b1110111111101010111010000000000000000 "
b1110111111101010111010000000000000000 1
b10011 %
1#
#1100000
b111011111110101011101000000000000000 "
b111011111110101011101000000000000000 1
0#
#1110000
b10100 %
b1111111111111 0
b1110111111110101011101000000000000000 "
b1110111111110101011101000000000000000 1
b10100 .
1#
#1120000
b111011111111010101110100000000000000 "
b111011111111010101110100000000000000 1
0#
#1130000
b10101 .
b111111111111 0
b1110111111111010101110100000000000000 "
b1110111111111010101110100000000000000 1
b10101 %
1#
#1140000
b111011111111101010111010000000000000 "
b111011111111101010111010000000000000 1
0#
#1150000
b10110 %
b11111111111 0
b1110111111111101010111010000000000000 "
b1110111111111101010111010000000000000 1
b10110 .
1#
#1160000
b111011111111110101011101000000000000 "
b111011111111110101011101000000000000 1
0#
#1170000
b10111 .
b1111111111 0
b1110111111111110101011101000000000000 "
b1110111111111110101011101000000000000 1
b10111 %
1#
#1180000
b111011111111111010101110100000000000 "
b111011111111111010101110100000000000 1
0#
#1190000
b11000 %
b111111111 0
b1110111111111111010101110100000000000 "
b1110111111111111010101110100000000000 1
b11000 .
1#
#1200000
b111011111111111101010111010000000000 "
b111011111111111101010111010000000000 1
0#
#1210000
b11001 .
b11111111 0
b1110111111111111101010111010000000000 "
b1110111111111111101010111010000000000 1
b11001 %
1#
#1220000
b111011111111111110101011101000000000 "
b111011111111111110101011101000000000 1
0#
#1230000
b11010 %
b1111111 0
b1110111111111111110101011101000000000 "
b1110111111111111110101011101000000000 1
b11010 .
1#
#1240000
b111011111111111111010101110100000000 "
b111011111111111111010101110100000000 1
0#
#1250000
b11011 .
b111111 0
b1110111111111111111010101110100000000 "
b1110111111111111111010101110100000000 1
b11011 %
1#
#1260000
b111011111111111111101010111010000000 "
b111011111111111111101010111010000000 1
0#
#1270000
b11100 %
b11111 0
b1110111111111111111101010111010000000 "
b1110111111111111111101010111010000000 1
b11100 .
1#
#1280000
b111011111111111111110101011101000000 "
b111011111111111111110101011101000000 1
0#
#1290000
b11101 .
b1111 0
b1110111111111111111110101011101000000 "
b1110111111111111111110101011101000000 1
b11101 %
1#
#1300000
b111011111111111111111010101110100000 "
b111011111111111111111010101110100000 1
0#
#1310000
b11110 %
b111 0
b1110111111111111111111010101110100000 "
b1110111111111111111111010101110100000 1
b11110 .
1#
#1320000
b111011111111111111111101010111010000 "
b111011111111111111111101010111010000 1
0#
#1330000
b11111 .
b11 0
b1110111111111111111111101010111010000 "
b1110111111111111111111101010111010000 1
b11111 %
1#
#1340000
b111011111111111111111110101011101000 "
b111011111111111111111110101011101000 1
0#
#1350000
b100000 %
b1 0
b1110111111111111111111110101011101000 "
b1110111111111111111111110101011101000 1
b100000 .
1#
#1360000
b111011111111111111111111010101110100 "
b111011111111111111111111010101110100 1
0#
#1370000
b100001 .
b0 0
b1110111111111111111111111010101110100 "
b1110111111111111111111111010101110100 1
1!
b100001 %
1#
#1380000
0#
#1390000
1&
b100010 %
0!
b100010 .
1#
#1400000
0#
#1410000
b0 .
b0 /
b0 "
b0 1
0&
b0 $
b1011010 (
b1011010 -
b11111111111111111111111111100010 '
b11111111111111111111111111100010 ,
b0 %
1#
b1011010 +
b1111111111111111111111111111111111111111111111111111111111100010 *
1)
#1420000
0#
#1430000
b1 %
b11111111111111111111111111111111111111111111111111111010101110100 $
b1011010 0
b11111111111111111111111111100010 /
b1 .
1#
0)
#1440000
0#
#1450000
b10 .
b101101 0
b10 %
1#
#1460000
0#
#1470000
b11 %
b10110 0
b111111111111111111111111111000100000000000000000000000000000000 "
b111111111111111111111111111000100000000000000000000000000000000 1
b11 .
1#
#1480000
b11111111111111111111111111100010000000000000000000000000000000 "
b11111111111111111111111111100010000000000000000000000000000000 1
0#
#1490000
b100 .
b1011 0
b100 %
1#
#1500000
b1111111111111111111111111110001000000000000000000000000000000 "
b1111111111111111111111111110001000000000000000000000000000000 1
0#
#1510000
b101 %
b101 0
b1001111111111111111111111110110101000000000000000000000000000000 "
b1001111111111111111111111110110101000000000000000000000000000000 1
b101 .
1#
#1520000
b100111111111111111111111111011010100000000000000000000000000000 "
b100111111111111111111111111011010100000000000000000000000000000 1
0#
#1530000
b110 .
b10 0
b1100111111111111111111111110011110100000000000000000000000000000 "
b1100111111111111111111111110011110100000000000000000000000000000 1
b110 %
1#
#1540000
b110011111111111111111111111001111010000000000000000000000000000 "
b110011111111111111111111111001111010000000000000000000000000000 1
0#
#1550000
b111 %
b1 0
b111 .
1#
#1560000
b11001111111111111111111111100111101000000000000000000000000000 "
b11001111111111111111111111100111101000000000000000000000000000 1
0#
#1570000
b1000 .
b0 0
b1011001111111111111111111110101011101000000000000000000000000000 "
b1011001111111111111111111110101011101000000000000000000000000000 1
b1000 %
1#
#1580000
b101100111111111111111111111010101110100000000000000000000000000 "
b101100111111111111111111111010101110100000000000000000000000000 1
0#
#1590000
b1001 %
b1001 .
1#
#1600000
b10110011111111111111111111101010111010000000000000000000000000 "
b10110011111111111111111111101010111010000000000000000000000000 1
0#
#1610000
b1010 .
b1010 %
1#
#1620000
b1011001111111111111111111110101011101000000000000000000000000 "
b1011001111111111111111111110101011101000000000000000000000000 1
0#
#1630000
b1011 %
b1011 .
1#
#1640000
b101100111111111111111111111010101110100000000000000000000000 "
b101100111111111111111111111010101110100000000000000000000000 1
0#
#1650000
b1100 .
b1100 %
1#
#1660000
b10110011111111111111111111101010111010000000000000000000000 "
b10110011111111111111111111101010111010000000000000000000000 1
0#
#1670000
b1101 %
b1101 .
1#
#1680000
b1011001111111111111111111110101011101000000000000000000000 "
b1011001111111111111111111110101011101000000000000000000000 1
0#
#1690000
b1110 .
b1110 %
1#
#1700000
b101100111111111111111111111010101110100000000000000000000 "
b101100111111111111111111111010101110100000000000000000000 1
0#
#1710000
b1111 %
b1111 .
1#
#1720000
b10110011111111111111111111101010111010000000000000000000 "
b10110011111111111111111111101010111010000000000000000000 1
0#
#1730000
b10000 .
b10000 %
1#
#1740000
b1011001111111111111111111110101011101000000000000000000 "
b1011001111111111111111111110101011101000000000000000000 1
0#
#1750000
b10001 %
b10001 .
1#
#1760000
b101100111111111111111111111010101110100000000000000000 "
b101100111111111111111111111010101110100000000000000000 1
0#
#1770000
b10010 .
b10010 %
1#
#1780000
b10110011111111111111111111101010111010000000000000000 "
b10110011111111111111111111101010111010000000000000000 1
0#
#1790000
b10011 %
b10011 .
1#
#1800000
b1011001111111111111111111110101011101000000000000000 "
b1011001111111111111111111110101011101000000000000000 1
0#
#1810000
b10100 .
b10100 %
1#
#1820000
b101100111111111111111111111010101110100000000000000 "
b101100111111111111111111111010101110100000000000000 1
0#
#1830000
b10101 %
b10101 .
1#
#1840000
b10110011111111111111111111101010111010000000000000 "
b10110011111111111111111111101010111010000000000000 1
0#
#1850000
b10110 .
b10110 %
1#
#1860000
b1011001111111111111111111110101011101000000000000 "
b1011001111111111111111111110101011101000000000000 1
0#
#1870000
b10111 %
b10111 .
1#
#1880000
b101100111111111111111111111010101110100000000000 "
b101100111111111111111111111010101110100000000000 1
0#
#1890000
b11000 .
b11000 %
1#
#1900000
b10110011111111111111111111101010111010000000000 "
b10110011111111111111111111101010111010000000000 1
0#
#1910000
b11001 %
b11001 .
1#
#1920000
b1011001111111111111111111110101011101000000000 "
b1011001111111111111111111110101011101000000000 1
0#
#1930000
b11010 .
b11010 %
1#
#1940000
b101100111111111111111111111010101110100000000 "
b101100111111111111111111111010101110100000000 1
0#
#1950000
b11011 %
b11011 .
1#
#1960000
b10110011111111111111111111101010111010000000 "
b10110011111111111111111111101010111010000000 1
0#
#1970000
b11100 .
b11100 %
1#
#1980000
b1011001111111111111111111110101011101000000 "
b1011001111111111111111111110101011101000000 1
0#
#1990000
b11101 %
b11101 .
1#
#2000000
b101100111111111111111111111010101110100000 "
b101100111111111111111111111010101110100000 1
0#
#2010000
b11110 .
b11110 %
1#
#2020000
b10110011111111111111111111101010111010000 "
b10110011111111111111111111101010111010000 1
0#
#2030000
b11111 %
b11111 .
1#
#2040000
b1011001111111111111111111110101011101000 "
b1011001111111111111111111110101011101000 1
0#
#2050000
b100000 .
b100000 %
1#
#2060000
b101100111111111111111111111010101110100 "
b101100111111111111111111111010101110100 1
0#
#2070000
b100001 %
1!
b100001 .
1#
#2080000
0#
#2090000
b100010 .
0!
1&
b100010 %
1#
#2100000
0#
#2110000
0&
b0 $
b11111111111111111111111110100110 (
b11111111111111111111111110100110 -
b0 %
b0 /
b0 "
b0 1
b0 .
1#
b1111111111111111111111111111111111111111111111111111111110100110 +
1)
#2120000
0#
#2130000
b1 .
b11111111111111111111111110100110 0
b11111111111111111111111111100010 /
b1 %
b101010001100 $
1#
0)
#2140000
0#
#2150000
b10 %
b1111111111111111111111111010011 0
b10 .
1#
#2160000
0#
#2170000
b11 .
b111111111111111111111111101001 0
b111111111111111111111111111000100000000000000000000000000000000 "
b111111111111111111111111111000100000000000000000000000000000000 1
b11 %
1#
#2180000
b11111111111111111111111111100010000000000000000000000000000000 "
b11111111111111111111111111100010000000000000000000000000000000 1
0#
#2190000
b100 %
b11111111111111111111111110100 0
b1011111111111111111111111110100110000000000000000000000000000000 "
b1011111111111111111111111110100110000000000000000000000000000000 1
b100 .
1#
#2200000
b101111111111111111111111111010011000000000000000000000000000000 "
b101111111111111111111111111010011000000000000000000000000000000 1
0#
#2210000
b101 .
b1111111111111111111111111010 0
b101 %
1#
#2220000
b10111111111111111111111111101001100000000000000000000000000000 "
b10111111111111111111111111101001100000000000000000000000000000 1
0#
#2230000
b110 %
b111111111111111111111111101 0
b110 .
1#
#2240000
b1011111111111111111111111110100110000000000000000000000000000 "
b1011111111111111111111111110100110000000000000000000000000000 1
0#
#2250000
b111 .
b11111111111111111111111110 0
b1001011111111111111111111110111000110000000000000000000000000000 "
b1001011111111111111111111110111000110000000000000000000000000000 1
b111 %
1#
#2260000
b100101111111111111111111111011100011000000000000000000000000000 "
b100101111111111111111111111011100011000000000000000000000000000 1
0#
#2270000
b1000 %
b1111111111111111111111111 0
b1000 .
1#
#2280000
b10010111111111111111111111101110001100000000000000000000000000 "
b10010111111111111111111111101110001100000000000000000000000000 1
0#
#2290000
b1001 .
b111111111111111111111111 0
b1010010111111111111111111110110010001100000000000000000000000000 "
b1010010111111111111111111110110010001100000000000000000000000000 1
b1001 %
1#
#2300000
b101001011111111111111111111011001000110000000000000000000000000 "
b101001011111111111111111111011001000110000000000000000000000000 1
0#
#2310000
b1010 %
b11111111111111111111111 0
b1101001011111111111111111110011101000110000000000000000000000000 "
b1101001011111111111111111110011101000110000000000000000000000000 1
b1010 .
1#
#2320000
b110100101111111111111111111001110100011000000000000000000000000 "
b110100101111111111111111111001110100011000000000000000000000000 1
0#
#2330000
b1011 .
b1111111111111111111111 0
b1110100101111111111111111110010010100011000000000000000000000000 "
b1110100101111111111111111110010010100011000000000000000000000000 1
b1011 %
1#
#2340000
b111010010111111111111111111001001010001100000000000000000000000 "
b111010010111111111111111111001001010001100000000000000000000000 1
0#
#2350000
b1100 %
b111111111111111111111 0
b1111010010111111111111111110001101010001100000000000000000000000 "
b1111010010111111111111111110001101010001100000000000000000000000 1
b1100 .
1#
#2360000
b111101001011111111111111111000110101000110000000000000000000000 "
b111101001011111111111111111000110101000110000000000000000000000 1
0#
#2370000
b1101 .
b11111111111111111111 0
b1111101001011111111111111110001010101000110000000000000000000000 "
b1111101001011111111111111110001010101000110000000000000000000000 1
b1101 %
1#
#2380000
b111110100101111111111111111000101010100011000000000000000000000 "
b111110100101111111111111111000101010100011000000000000000000000 1
0#
#2390000
b1110 %
b1111111111111111111 0
b1111110100101111111111111110001001010100011000000000000000000000 "
b1111110100101111111111111110001001010100011000000000000000000000 1
b1110 .
1#
#2400000
b111111010010111111111111111000100101010001100000000000000000000 "
b111111010010111111111111111000100101010001100000000000000000000 1
0#
#2410000
b1111 .
b111111111111111111 0
b1111111010010111111111111110001000101010001100000000000000000000 "
b1111111010010111111111111110001000101010001100000000000000000000 1
b1111 %
1#
#2420000
b111111101001011111111111111000100010101000110000000000000000000 "
b111111101001011111111111111000100010101000110000000000000000000 1
0#
#2430000
b10000 %
b11111111111111111 0
b1111111101001011111111111110001000010101000110000000000000000000 "
b1111111101001011111111111110001000010101000110000000000000000000 1
b10000 .
1#
#2440000
b111111110100101111111111111000100001010100011000000000000000000 "
b111111110100101111111111111000100001010100011000000000000000000 1
0#
#2450000
b10001 .
b1111111111111111 0
b1111111110100101111111111110001000001010100011000000000000000000 "
b1111111110100101111111111110001000001010100011000000000000000000 1
b10001 %
1#
#2460000
b111111111010010111111111111000100000101010001100000000000000000 "
b111111111010010111111111111000100000101010001100000000000000000 1
0#
#2470000
b10010 %
b111111111111111 0
b1111111111010010111111111110001000000101010001100000000000000000 "
b1111111111010010111111111110001000000101010001100000000000000000 1
b10010 .
1#
#2480000
b111111111101001011111111111000100000010101000110000000000000000 "
b111111111101001011111111111000100000010101000110000000000000000 1
0#
#2490000
b10011 .
b11111111111111 0
b1111111111101001011111111110001000000010101000110000000000000000 "
b1111111111101001011111111110001000000010101000110000000000000000 1
b10011 %
1#
#2500000
b111111111110100101111111111000100000001010100011000000000000000 "
b111111111110100101111111111000100000001010100011000000000000000 1
0#
#2510000
b10100 %
b1111111111111 0
b1111111111110100101111111110001000000001010100011000000000000000 "
b1111111111110100101111111110001000000001010100011000000000000000 1
b10100 .
1#
#2520000
b111111111111010010111111111000100000000101010001100000000000000 "
b111111111111010010111111111000100000000101010001100000000000000 1
0#
#2530000
b10101 .
b111111111111 0
b1111111111111010010111111110001000000000101010001100000000000000 "
b1111111111111010010111111110001000000000101010001100000000000000 1
b10101 %
1#
#2540000
b111111111111101001011111111000100000000010101000110000000000000 "
b111111111111101001011111111000100000000010101000110000000000000 1
0#
#2550000
b10110 %
b11111111111 0
b1111111111111101001011111110001000000000010101000110000000000000 "
b1111111111111101001011111110001000000000010101000110000000000000 1
b10110 .
1#
#2560000
b111111111111110100101111111000100000000001010100011000000000000 "
b111111111111110100101111111000100000000001010100011000000000000 1
0#
#2570000
b10111 .
b1111111111 0
b1111111111111110100101111110001000000000001010100011000000000000 "
b1111111111111110100101111110001000000000001010100011000000000000 1
b10111 %
1#
#2580000
b111111111111111010010111111000100000000000101010001100000000000 "
b111111111111111010010111111000100000000000101010001100000000000 1
0#
#2590000
b11000 %
b111111111 0
b1111111111111111010010111110001000000000000101010001100000000000 "
b1111111111111111010010111110001000000000000101010001100000000000 1
b11000 .
1#
#2600000
b111111111111111101001011111000100000000000010101000110000000000 "
b111111111111111101001011111000100000000000010101000110000000000 1
0#
#2610000
b11001 .
b11111111 0
b1111111111111111101001011110001000000000000010101000110000000000 "
b1111111111111111101001011110001000000000000010101000110000000000 1
b11001 %
1#
#2620000
b111111111111111110100101111000100000000000001010100011000000000 "
b111111111111111110100101111000100000000000001010100011000000000 1
0#
#2630000
b11010 %
b1111111 0
b1111111111111111110100101110001000000000000001010100011000000000 "
b1111111111111111110100101110001000000000000001010100011000000000 1
b11010 .
1#
#2640000
b111111111111111111010010111000100000000000000101010001100000000 "
b111111111111111111010010111000100000000000000101010001100000000 1
0#
#2650000
b11011 .
b111111 0
b1111111111111111111010010110001000000000000000101010001100000000 "
b1111111111111111111010010110001000000000000000101010001100000000 1
b11011 %
1#
#2660000
b111111111111111111101001011000100000000000000010101000110000000 "
b111111111111111111101001011000100000000000000010101000110000000 1
0#
#2670000
b11100 %
b11111 0
b1111111111111111111101001010001000000000000000010101000110000000 "
b1111111111111111111101001010001000000000000000010101000110000000 1
b11100 .
1#
#2680000
b111111111111111111110100101000100000000000000001010100011000000 "
b111111111111111111110100101000100000000000000001010100011000000 1
0#
#2690000
b11101 .
b1111 0
b1111111111111111111110100100001000000000000000001010100011000000 "
b1111111111111111111110100100001000000000000000001010100011000000 1
b11101 %
1#
#2700000
b111111111111111111111010010000100000000000000000101010001100000 "
b111111111111111111111010010000100000000000000000101010001100000 1
0#
#2710000
b11110 %
b111 0
b1111111111111111111111010001001000000000000000000101010001100000 "
b1111111111111111111111010001001000000000000000000101010001100000 1
b11110 .
1#
#2720000
b111111111111111111111101000100100000000000000000010101000110000 "
b111111111111111111111101000100100000000000000000010101000110000 1
0#
#2730000
b11111 .
b11 0
b1111111111111111111111100111101000000000000000000010101000110000 "
b1111111111111111111111100111101000000000000000000010101000110000 1
b11111 %
1#
#2740000
b111111111111111111111110011110100000000000000000001010100011000 "
b111111111111111111111110011110100000000000000000001010100011000 1
0#
#2750000
b100000 %
b1 0
b1111111111111111111111110010111000000000000000000001010100011000 "
b1111111111111111111111110010111000000000000000000001010100011000 1
b100000 .
1#
#2760000
b111111111111111111111111001011100000000000000000000101010001100 "
b111111111111111111111111001011100000000000000000000101010001100 1
0#
#2770000
b100001 .
b0 0
b1111111111111111111111111000100000000000000000000000101010001100 "
b1111111111111111111111111000100000000000000000000000101010001100 1
1!
b100001 %
1#
#2780000
0#
#2790000
1&
b100010 %
0!
b100010 .
1#
#2800000
0#
#2810000
b0 .
b0 /
b0 "
b0 1
0&
b0 $
b11111111111111111111111111111111 (
b11111111111111111111111111111111 -
b11111111111111111111111111111111 '
b11111111111111111111111111111111 ,
b0 %
1#
b11111111111111111111111111111111 +
b11111111111111111111111111111111 *
1)
#2820000
0#
#2830000
b1 %
b1111111111111111111111111111111000000000000000000000000000000001 $
b11111111111111111111111111111111 0
b11111111111111111111111111111111 /
b1 .
1#
0)
#2840000
0#
#2850000
b10 .
b1111111111111111111111111111111 0
b111111111111111111111111111111110000000000000000000000000000000 "
b111111111111111111111111111111110000000000000000000000000000000 1
b10 %
1#
#2860000
b11111111111111111111111111111111000000000000000000000000000000 "
b11111111111111111111111111111111000000000000000000000000000000 1
0#
